[
  {
    "name": "Politiciens en Guerre Froide",
    "theme": "Politique",
    "questions": [
      1717364676395.4236,
      1717364739676.499
    ],
    "selfStats": 1717364595334.2634,
    "photo": "none",
    "id": 1717364595336.695
  },
  {
    "name": "Calcul mental",
    "theme": "Mathématiques",
    "questions": [
      1717364874796.388,
      1717364895688.5945,
      1717364920023.7563
    ],
    "selfStats": 1717364840134.3032,
    "photo": "./assets/quiz/Calcul_mental.png",
    "id": 1717364840135.3843
  },
  {
    "name": "Recettes provinciales ",
    "theme": "Cuisine",
    "questions": [
      1717365094798.9285,
      1717365232934.2886
    ],
    "selfStats": 1717365043113.405,
    "photo": "none",
    "id": 1717365043114.6316
  }
]